{
  "openapi": "3.0.4",
  "info": {
    "title": "Election Service API",
    "version": "0.1.0",
    "description": "Election lifecycle and candidate management for the vote system POC."
  },
  "servers": [
    {
      "url": "https://election-api.vote-system-example.com",
      "description": "Production placeholder"
    }
  ],
  "tags": [
    {
      "name": "Elections",
      "description": "Election operations"
    }
  ],
  "paths": {
    "/api/v1/elections": {
      "post": {
        "tags": ["Elections"],
        "summary": "Create a new election",
        "security": [
          {
            "bearerAuth": []
          }
        ],
        "requestBody": {
          "required": true,
          "content": {
            "application/json": {
              "schema": {
                "$ref": "#/components/schemas/ElectionRequest"
              },
              "examples": {
                "default": {
                  "value": {
                    "name": "Finals 2025",
                    "startTime": "2025-06-01T20:00:00Z",
                    "endTime": "2025-06-01T21:00:00Z",
                    "candidates": [
                      {
                        "name": "Candidate A"
                      },
                      {
                        "name": "Candidate B"
                      }
                    ]
                  }
                }
              }
            }
          }
        },
        "responses": {
          "201": {
            "description": "Election created",
            "content": {
              "application/json": {
                "schema": {
                  "$ref": "#/components/schemas/ElectionResponse"
                }
              }
            }
          },
          "400": {
            "description": "Invalid election payload",
            "content": {
              "application/json": {
                "schema": {
                  "$ref": "#/components/schemas/ErrorResponse"
                }
              }
            }
          },
          "401": {
            "description": "Unauthorized",
            "content": {
              "application/json": {
                "schema": {
                  "$ref": "#/components/schemas/ErrorResponse"
                }
              }
            }
          }
        }
      }
    },
    "/api/v1/elections/{id}": {
      "get": {
        "tags": ["Elections"],
        "summary": "Retrieve election by id",
        "parameters": [
          {
            "in": "path",
            "name": "id",
            "required": true,
            "schema": {
              "type": "string",
              "format": "uuid"
            }
          }
        ],
        "responses": {
          "200": {
            "description": "Election found",
            "content": {
              "application/json": {
                "schema": {
                  "$ref": "#/components/schemas/ElectionResponse"
                }
              }
            }
          },
          "400": {
            "description": "Invalid id",
            "content": {
              "application/json": {
                "schema": {
                  "$ref": "#/components/schemas/ErrorResponse"
                }
              }
            }
          },
          "404": {
            "description": "Election not found",
            "content": {
              "application/json": {
                "schema": {
                  "$ref": "#/components/schemas/ErrorResponse"
                }
              }
            }
          }
        }
      },
      "put": {
        "tags": ["Elections"],
        "summary": "Update an existing election",
        "security": [
          {
            "bearerAuth": []
          }
        ],
        "parameters": [
          {
            "in": "path",
            "name": "id",
            "required": true,
            "schema": {
              "type": "string",
              "format": "uuid"
            }
          }
        ],
        "requestBody": {
          "required": true,
          "content": {
            "application/json": {
              "schema": {
                "$ref": "#/components/schemas/ElectionRequest"
              }
            }
          }
        },
        "responses": {
          "200": {
            "description": "Election updated",
            "content": {
              "application/json": {
                "schema": {
                  "$ref": "#/components/schemas/ElectionResponse"
                }
              }
            }
          },
          "400": {
            "description": "Invalid election data",
            "content": {
              "application/json": {
                "schema": {
                  "$ref": "#/components/schemas/ErrorResponse"
                }
              }
            }
          },
          "401": {
            "description": "Unauthorized",
            "content": {
              "application/json": {
                "schema": {
                  "$ref": "#/components/schemas/ErrorResponse"
                }
              }
            }
          },
          "404": {
            "description": "Election not found",
            "content": {
              "application/json": {
                "schema": {
                  "$ref": "#/components/schemas/ErrorResponse"
                }
              }
            }
          }
        }
      },
      "delete": {
        "tags": ["Elections"],
        "summary": "Delete an election",
        "security": [
          {
            "bearerAuth": []
          }
        ],
        "parameters": [
          {
            "in": "path",
            "name": "id",
            "required": true,
            "schema": {
              "type": "string",
              "format": "uuid"
            }
          }
        ],
        "responses": {
          "204": {
            "description": "Election deleted"
          },
          "401": {
            "description": "Unauthorized",
            "content": {
              "application/json": {
                "schema": {
                  "$ref": "#/components/schemas/ErrorResponse"
                }
              }
            }
          },
          "404": {
            "description": "Election not found",
            "content": {
              "application/json": {
                "schema": {
                  "$ref": "#/components/schemas/ErrorResponse"
                }
              }
            }
          }
        }
      }
    },
    "/api/v1/elections/{electionId}/candidates": {
      "get": {
        "tags": ["Elections"],
        "summary": "List candidates for an election",
        "parameters": [
          {
            "in": "path",
            "name": "electionId",
            "required": true,
            "schema": {
              "type": "string",
              "format": "uuid"
            }
          }
        ],
        "responses": {
          "200": {
            "description": "Candidates list",
            "content": {
              "application/json": {
                "schema": {
                  "type": "array",
                  "items": {
                    "$ref": "#/components/schemas/Candidate"
                  }
                }
              }
            }
          },
          "400": {
            "description": "Invalid election id",
            "content": {
              "application/json": {
                "schema": {
                  "$ref": "#/components/schemas/ErrorResponse"
                }
              }
            }
          },
          "404": {
            "description": "Election not found",
            "content": {
              "application/json": {
                "schema": {
                  "$ref": "#/components/schemas/ErrorResponse"
                }
              }
            }
          }
        }
      }
    }
  },
  "components": {
    "securitySchemes": {
      "bearerAuth": {
        "type": "http",
        "scheme": "bearer",
        "bearerFormat": "JWT"
      }
    },
    "schemas": {
      "ElectionRequest": {
        "type": "object",
        "required": ["name", "startTime", "endTime", "candidates"],
        "properties": {
          "name": {
            "type": "string"
          },
          "startTime": {
            "type": "string",
            "format": "date-time"
          },
          "endTime": {
            "type": "string",
            "format": "date-time"
          },
          "candidates": {
            "type": "array",
            "minItems": 2,
            "items": {
              "type": "object",
              "required": ["name"],
              "properties": {
                "name": {
                  "type": "string"
                }
              }
            }
          }
        }
      },
      "ElectionResponse": {
        "type": "object",
        "required": ["id", "name", "startTime", "endTime"],
        "properties": {
          "id": {
            "type": "string",
            "format": "uuid"
          },
          "name": {
            "type": "string"
          },
          "startTime": {
            "type": "string",
            "format": "date-time"
          },
          "endTime": {
            "type": "string",
            "format": "date-time"
          },
          "status": {
            "type": "string",
            "example": "scheduled"
          }
        }
      },
      "Candidate": {
        "type": "object",
        "required": ["id", "name"],
        "properties": {
          "id": {
            "type": "string",
            "format": "uuid"
          },
          "name": {
            "type": "string"
          }
        }
      },
      "ErrorResponse": {
        "type": "object",
        "required": ["code", "message"],
        "properties": {
          "code": {
            "type": "string",
            "example": "ELECTION_NOT_FOUND"
          },
          "message": {
            "type": "string"
          },
          "traceId": {
            "type": "string",
            "description": "Correlation id for troubleshooting"
          }
        }
      }
    }
  }
}
